heyyou/__init__.py
heyyou/main.py
heyyou-0.0.4.dist-info/LICENSE
heyyou-0.0.4.dist-info/METADATA
heyyou-0.0.4.dist-info/WHEEL
heyyou-0.0.4.dist-info/entry_points.txt
heyyou-0.0.4.dist-info/top_level.txt
heyyou-0.0.4.dist-info/RECORD
