Metadata-Version: 2.1
Name: heyyou
Version: 0.0.4
Summary: A command line application that prints out 'Hey, You!' in the chosen language.
Author-email: Zaid Waqi <zaidwaqi@gmail.com>
License: MIT
Project-URL: Homepage, https://github.com/zaidwaqi/heyyou
Project-URL: Issues, https://github.com/pypa/zaidwaqi/heyyou/issues
Classifier: Programming Language :: Python :: 3
Classifier: License :: OSI Approved :: MIT License
Classifier: Operating System :: OS Independent
Requires-Python: >=3.11
License-File: LICENSE
